pylabelbase/__init__.py
pylabelbase/api.py
pylabelbase-0.0.1.dist-info/LICENSE
pylabelbase-0.0.1.dist-info/METADATA
pylabelbase-0.0.1.dist-info/WHEEL
pylabelbase-0.0.1.dist-info/top_level.txt
pylabelbase-0.0.1.dist-info/RECORD
