Metadata-Version: 2.1
Name: pylabelbase
Version: 0.0.1
License-File: LICENSE
Requires-Dist: requests
